mupl/__init__.py
mupl/__version__.py
mupl/cli.py
mupl/core.py
mupl/exceptions.py
mupl/file_validator.py
mupl/image_validator.py
mupl/updater.py
mupl/http/__init__.py
mupl/http/client.py
mupl/http/model.py
mupl/http/oauth.py
mupl/http/response.py
mupl/loc/__init__.py
mupl/loc/en.json
mupl/loc/load.py
mupl/uploader/__init__.py
mupl/uploader/handler.py
mupl/uploader/uploader.py
mupl/utils/__init__.py
mupl/utils/config.py
mupl/utils/logs.py
muplr-2.1.21.dist-info/licenses/LICENSE
muplr-2.1.21.dist-info/METADATA
muplr-2.1.21.dist-info/WHEEL
muplr-2.1.21.dist-info/top_level.txt
muplr-2.1.21.dist-info/RECORD
