Metadata-Version: 2.4
Name: muplr
Version: 2.1.21
Summary: mupl: Bulk MangaDex Upload Tool
Author: ArdaxHz
License-Expression: GPL-3.0-or-later
Project-URL: Homepage, https://github.com/ArdaxHz/mupl
Project-URL: Repository, https://github.com/ArdaxHz/mupl
Project-URL: Bug Tracker, https://github.com/ArdaxHz/mupl/issues
Keywords: manga,upload,bulk,mangadex
Classifier: Development Status :: 5 - Production/Stable
Classifier: Programming Language :: Python :: 3
Classifier: Programming Language :: Python :: 3.10
Classifier: Programming Language :: Python :: 3.11
Classifier: Programming Language :: Python :: 3.12
Classifier: Operating System :: OS Independent
Classifier: Intended Audience :: End Users/Desktop
Classifier: Topic :: Games/Entertainment
Classifier: Topic :: Internet :: WWW/HTTP
Classifier: Topic :: Multimedia
Classifier: Topic :: Utilities
Requires-Python: >=3.10
License-File: LICENSE
Requires-Dist: requests
Requires-Dist: natsort
Requires-Dist: packaging
Requires-Dist: Pillow
Requires-Dist: tqdm
Dynamic: license-file
